pygda/__init__.py
pygda/version.py
pygda/datasets/__init__.py
pygda/datasets/airport.py
pygda/datasets/arxiv.py
pygda/datasets/blog.py
pygda/datasets/citation.py
pygda/datasets/elliptic.py
pygda/datasets/facebook.py
pygda/datasets/mag.py
pygda/datasets/squirrel.py
pygda/datasets/tugraph.py
pygda/datasets/twitch.py
pygda/datasets/twitter.py
pygda/datasets/webkb.py
pygda/metrics/__init__.py
pygda/metrics/metrics.py
pygda/models/__init__.py
pygda/models/a2gnn.py
pygda/models/acdne.py
pygda/models/adagcn.py
pygda/models/asn.py
pygda/models/base.py
pygda/models/cwgcn.py
pygda/models/dane.py
pygda/models/dgda.py
pygda/models/dgsda.py
pygda/models/dmgnn.py
pygda/models/gnn.py
pygda/models/grade.py
pygda/models/graphata.py
pygda/models/graphcta.py
pygda/models/gtrans.py
pygda/models/jhgda.py
pygda/models/kbl.py
pygda/models/pa.py
pygda/models/sagda.py
pygda/models/sepa.py
pygda/models/soga.py
pygda/models/specreg.py
pygda/models/strurw.py
pygda/models/tdss.py
pygda/models/udagcn.py
pygda/nn/__init__.py
pygda/nn/a2gnn_base.py
pygda/nn/acdne_base.py
pygda/nn/adagcn_base.py
pygda/nn/asn_base.py
pygda/nn/attention.py
pygda/nn/cached_gcn_conv.py
pygda/nn/cwgcn_base.py
pygda/nn/deepwalk_pretrain.py
pygda/nn/dgda_base.py
pygda/nn/dgsda_base.py
pygda/nn/gmm_clustering.py
pygda/nn/gnn_base.py
pygda/nn/grade_base.py
pygda/nn/graphata_base.py
pygda/nn/jhgda_base.py
pygda/nn/kbl_base.py
pygda/nn/mixup_base.py
pygda/nn/mixup_gcnconv.py
pygda/nn/node_centric_conv.py
pygda/nn/ppmi_conv.py
pygda/nn/prop_gcn_conv.py
pygda/nn/reverse_layer.py
pygda/nn/reweight_gnn.py
pygda/nn/sagda_base.py
pygda/nn/soga_base.py
pygda/nn/udagcn_base.py
pygda/utils/__init__.py
pygda/utils/mmd.py
pygda/utils/perturb.py
pygda/utils/sampler.py
pygda/utils/svd_transform.py
pygda/utils/utility.py
pygda-1.2.1.dist-info/licenses/LICENSE
pygda-1.2.1.dist-info/WHEEL
pygda-1.2.1.dist-info/METADATA
pygda-1.2.1.dist-info/RECORD
