Metadata-Version: 2.4
Name: pygda
Version: 1.2.1
Summary: A Python library for Graph Domain Adaptation
Author: pygda-team
Classifier: Programming Language :: Python :: 3
Classifier: License :: OSI Approved :: MIT License
Classifier: Operating System :: OS Independent
License-File: LICENSE
Requires-Dist: numpy
Requires-Dist: scikit-learn
Requires-Dist: scipy
Requires-Dist: tqdm
Project-URL: Repository, https://github.com/pygda-team/pygda
